{
    "projectName": "HL7 FHIR Profile: Skin and Wound Assessment (SW), Release 1 (For Comment)",
    "projectShorthand": "SWA",
    "projectURL": "http://hl7.org/fhir/us/swa",
    "fhirURL": "http://hl7.org/fhir/us/swa",
    "entryTypeURL": "http://hl7.org/fhir/us/swa/spec",

    "implementationGuide":
	{
        "npmName": "hl7.fhir.us.swa",
        "version": "1.0.0",
		"includeLogicalModels": true,
		"includeModelDoc": false,
		"indexContent": "LandingPageWound.html",
		"primarySelectionStrategy":
		{
            "strategy": "namespace",
            "primary": ["swa"],
            "hideSupporting": true
		}
	},
	"filterStrategy":
	{
        "filter": true,
		"strategy": "namespace",
		"target": ["swa"]
	},
    "publisher": "HL7 Patient Care and Clinical Information Modeling Initiative Work Groups",
    "contact": [
        {
            "telecom": [
                {
                    "system": "url",
                    "value": "http://standardhealthrecord.org"
                }
            ]
        }
    ]
}